bifis/__init__.py
bifis/sampling.py
bifis/utils.py
bifis/geometry/__init__.py
bifis/geometry/bb.py
bifis/geometry/sdf.py
bifis-0.1.0.dist-info/METADATA
bifis-0.1.0.dist-info/WHEEL
bifis-0.1.0.dist-info/licenses/LICENSE
bifis-0.1.0.dist-info/RECORD
