Metadata-Version: 2.4
Name: bifis
Version: 0.1.0
Summary: A CFD image sampling library.
Project-URL: Homepage, https://github.com/omaralvarez/gentab
Project-URL: Issues, https://github.com/omaralvarez/gentab/issues
Author-email: "Omar A. Mures" <omar.alvarez@udc.es>
License-File: LICENSE
Keywords: bifis,cfd,image,machine learning,sampling,sdf
Classifier: License :: OSI Approved :: GNU General Public License v2 or later (GPLv2+)
Classifier: Operating System :: OS Independent
Classifier: Programming Language :: Python :: 3
Requires-Python: >=3.9
Requires-Dist: matplotlib
Requires-Dist: numpy>=2.0.0
Requires-Dist: rich
Requires-Dist: scipy
Provides-Extra: dev
Requires-Dist: black; extra == 'dev'
